melobot_protocol_onebot-1.0.0rc3.dist-info/METADATA
melobot_protocol_onebot-1.0.0rc3.dist-info/WHEEL
melobot_protocol_onebot-1.0.0rc3.dist-info/entry_points.txt
melobot_protocol_onebot-1.0.0rc3.dist-info/licenses/LICENSE
melobot_protocol_onebot/__init__.py
melobot_protocol_onebot/v11/__init__.py
melobot_protocol_onebot/v11/adapter/__init__.py
melobot_protocol_onebot/v11/adapter/action.py
melobot_protocol_onebot/v11/adapter/base.py
melobot_protocol_onebot/v11/adapter/echo.py
melobot_protocol_onebot/v11/adapter/event.py
melobot_protocol_onebot/v11/adapter/segment.py
melobot_protocol_onebot/v11/const.py
melobot_protocol_onebot/v11/handle.py
melobot_protocol_onebot/v11/io/__init__.py
melobot_protocol_onebot/v11/io/base.py
melobot_protocol_onebot/v11/io/duplex_http.py
melobot_protocol_onebot/v11/io/forward.py
melobot_protocol_onebot/v11/io/packet.py
melobot_protocol_onebot/v11/io/reverse.py
melobot_protocol_onebot/v11/utils/__init__.py
melobot_protocol_onebot/v11/utils/abc.py
melobot_protocol_onebot/v11/utils/check.py
melobot_protocol_onebot/v11/utils/match.py
melobot_protocol_onebot/v11/utils/parse.py
melobot_protocol_onebot/v12/__init__.py
melobot_protocol_onebot-1.0.0rc3.dist-info/RECORD
