Metadata-Version: 2.1
Name: melobot-protocol-onebot
Version: 1.0.0rc3
Summary: IO and adapter layer implementation of onebot protocol for melobot.
Keywords: melobot,bot framework,asyncio,coroutine,concurrency
Author-Email: aicorein <aicorein@meloland.org>
Maintainer-Email: aicorein <aicorein@meloland.org>
License: BSD
Classifier: Development Status :: 4 - Beta
Classifier: Environment :: Console
Classifier: Intended Audience :: Developers
Classifier: License :: OSI Approved :: BSD License
Classifier: Operating System :: OS Independent
Classifier: Programming Language :: Python :: 3
Classifier: Programming Language :: Python :: 3.10
Classifier: Programming Language :: Python :: 3.11
Classifier: Programming Language :: Python :: 3.12
Classifier: Programming Language :: Python :: 3.13
Classifier: Programming Language :: Python :: Implementation :: CPython
Classifier: Topic :: Software Development :: Libraries :: Python Modules
Classifier: Typing :: Typed
Project-URL: Homepage, https://github.com/Meloland/melobot-protocol-onebot
Project-URL: Repository, https://github.com/Meloland/melobot-protocol-onebot.git
Project-URL: Issues, https://github.com/Meloland/melobot-protocol-onebot/issues
Requires-Python: >=3.10
Requires-Dist: melobot>=3.0.0rc4
Requires-Dist: pydantic<3,>=2.8.2
Requires-Dist: typing-extensions>=4.12.2
Requires-Dist: websockets>=13.0.1
Requires-Dist: aiohttp>=3.10.5
